provide_dir/__init__.py
provide_dir/version.py
provide_dir-0.1.2.dist-info/LICENSE
provide_dir-0.1.2.dist-info/METADATA
provide_dir-0.1.2.dist-info/WHEEL
provide_dir-0.1.2.dist-info/top_level.txt
provide_dir-0.1.2.dist-info/RECORD
