Metadata-Version: 2.1
Name: provide-dir
Version: 0.1.2
Summary: Provides a directory with all its parent directories, if it does not yet exist
Home-page: https://github.com/Nagidal/provide_dir
Author: Sven Siegmund
Author-email: sven.siegmund@gmail.com
License: UNKNOWN
Keywords: mkdir,make dir,make directory,recursive
Platform: any
Classifier: Development Status :: 5 - Production/Stable
Classifier: Intended Audience :: End Users/Desktop
Classifier: Intended Audience :: Developers
Classifier: Intended Audience :: System Administrators
Classifier: Environment :: Console
Classifier: Topic :: Software Development :: Testing
Classifier: License :: OSI Approved :: MIT License
Classifier: Natural Language :: English
Classifier: Programming Language :: Python :: 3.9
Classifier: Operating System :: OS Independent
Classifier: Operating System :: Microsoft :: Windows
Classifier: Operating System :: POSIX :: Linux
Classifier: Operating System :: MacOS :: MacOS X
Requires-Python: >=3.9
License-File: LICENSE
